<?xml version="1.0" encoding="utf-8"?><index><stem n="_key.p7b"><phr n="_Key.p7b"><ent r="3" t="1176" w="1379" /></phr></stem><stem n="p7b"><phr n="p7b"><ent r="3" t="1176" w="1379" /><ent r="3" t="1176" w="1386" /><ent r="5" t="1176" w="2231" /><ent r="3" t="1176" w="2245" /><ent r="5" t="1176" w="2333" /><ent r="5" t="1176" w="2338" /><ent r="5" t="1176" w="2374" /><ent r="5" t="1176" w="2422" /></phr></stem><stem n="-outform"><phr n="-outform"><ent r="3" t="1176" w="1380" /><ent r="3" t="1176" w="1380" /></phr></stem><stem n="outform"><phr n="outform"><ent r="3" t="1176" w="1380" /></phr></stem><stem n="key-pem"><phr n="Key-pem"><ent r="3" t="1176" w="1384" /></phr></stem><stem n="_key-pem.p7b"><phr n="_Key-pem.p7b"><ent r="3" t="1176" w="1386" /></phr></stem><stem n="myserv"><phr n="myserver"><ent r="3" t="1176" w="1414" /><ent r="3" t="1176" w="1469" /><ent r="5" t="1176" w="2275" /><ent r="5" t="1176" w="2322" /><ent r="5" t="1176" w="2361" /><ent r="5" t="1176" w="2404" /></phr></stem><stem n="@myserver:~/luna-keystores$"><phr n="@myserver:~/luna-keystores$"><ent r="3" t="1176" w="1416" /><ent r="3" t="1176" w="1471" /></phr></stem><stem n="-client2.crt"><phr n="-client2.crt"><ent r="3" t="1176" w="1432" /><ent r="3" t="1176" w="1432" /></phr></stem><stem n="(“certif"><phr n="(“Certificate"><ent r="3" t="1176" w="1463" /></phr></stem><stem n=":07:00"><phr n=":07:00"><ent r="3" t="1176" w="1699" /><ent r="3" t="1176" w="1708" /></phr></stem><stem n=":f0:9e:bc:eb:6a:88:2b:87:3a:76:35:7c:de:4b:b4"><phr n=":F0:9E:BC:EB:6A:88:2B:87:3A:76:35:7C:DE:4B:B4"><ent r="3" t="1176" w="1731" /></phr></stem><stem n=":0c:bc:e3:a1:97:e4:8b:24:2d:44:43:7a:ea:71:52:b3:c3:20:d7"><phr n=":0C:BC:E3:A1:97:E4:8B:24:2D:44:43:7A:EA:71:52:B3:C3:20:D7"><ent r="3" t="1176" w="1753" /></phr></stem><stem n="-importcert)."><phr n="-importcert)."><ent r="3" t="1176" w="1917" /><ent r="3" t="1176" w="1917" /></phr></stem><stem n="“single”"><phr n="“single”"><ent r="3" t="1176" w="1921" /></phr></stem><stem n="stack"><phr n="stacked"><ent r="3" t="1176" w="1927" /></phr></stem><stem n="“stacked”"><phr n="“stacked”"><ent r="3" t="1176" w="1928" /></phr></stem><stem n="#7."><phr n="#7."><ent r="3" t="1176" w="1948" /></phr></stem><stem n=".crt"><phr n=".crt"><ent r="4" t="1176" w="1958" /><ent r="4" t="1176" w="2039" /><ent r="4" t="1176" w="2053" /><ent r="4" t="1176" w="2356" /></phr></stem><stem n="-----begin"><phr n="-----BEGIN"><ent r="5" t="1176" w="1976" /><ent r="5" t="1176" w="1980" /><ent r="5" t="1176" w="2115" /><ent r="5" t="1176" w="2119" /><ent r="5" t="1176" w="2139" /><ent r="5" t="1176" w="2143" /><ent r="5" t="1176" w="2163" /><ent r="5" t="1176" w="2167" /></phr></stem><stem n="-----"><phr n="-----"><ent r="5" t="1176" w="1977" /><ent r="5" t="1176" w="1981" /><ent r="5" t="1176" w="1989" /><ent r="5" t="1176" w="1993" /><ent r="5" t="1176" w="2116" /><ent r="5" t="1176" w="2120" /><ent r="5" t="1176" w="2132" /><ent r="5" t="1176" w="2136" /><ent r="5" t="1176" w="2140" /><ent r="5" t="1176" w="2144" /><ent r="5" t="1176" w="2156" /><ent r="5" t="1176" w="2160" /><ent r="5" t="1176" w="2164" /><ent r="5" t="1176" w="2168" /><ent r="5" t="1176" w="2181" /><ent r="5" t="1176" w="2185" /></phr></stem><stem n="certificate-"><phr n="CERTIFICATE-"><ent r="5" t="1176" w="1977" /><ent r="5" t="1176" w="1989" /><ent r="5" t="1176" w="2116" /><ent r="5" t="1176" w="2132" /><ent r="5" t="1176" w="2140" /><ent r="5" t="1176" w="2156" /><ent r="5" t="1176" w="2164" /><ent r="5" t="1176" w="2181" /></phr></stem><stem n="certificate--"><phr n="CERTIFICATE--"><ent r="5" t="1176" w="1977" /><ent r="5" t="1176" w="1989" /><ent r="5" t="1176" w="2116" /><ent r="5" t="1176" w="2132" /><ent r="5" t="1176" w="2140" /><ent r="5" t="1176" w="2156" /><ent r="5" t="1176" w="2164" /><ent r="5" t="1176" w="2181" /></phr></stem><stem n="certificate---"><phr n="CERTIFICATE---"><ent r="5" t="1176" w="1977" /><ent r="5" t="1176" w="1989" /><ent r="5" t="1176" w="2116" /><ent r="5" t="1176" w="2132" /><ent r="5" t="1176" w="2140" /><ent r="5" t="1176" w="2156" /><ent r="5" t="1176" w="2164" /><ent r="5" t="1176" w="2181" /></phr></stem><stem n="certificate----"><phr n="CERTIFICATE----"><ent r="5" t="1176" w="1977" /><ent r="5" t="1176" w="1989" /><ent r="5" t="1176" w="2116" /><ent r="5" t="1176" w="2132" /><ent r="5" t="1176" w="2140" /><ent r="5" t="1176" w="2156" /><ent r="5" t="1176" w="2164" /><ent r="5" t="1176" w="2181" /></phr></stem><stem n="certificate-----"><phr n="CERTIFICATE-----"><ent r="5" t="1176" w="1977" /><ent r="5" t="1176" w="1989" /><ent r="5" t="1176" w="2116" /><ent r="5" t="1176" w="2132" /><ent r="5" t="1176" w="2140" /><ent r="5" t="1176" w="2156" /><ent r="5" t="1176" w="2164" /><ent r="5" t="1176" w="2181" /></phr></stem><stem n="-----end"><phr n="-----END"><ent r="5" t="1176" w="1988" /><ent r="5" t="1176" w="1992" /><ent r="5" t="1176" w="2131" /><ent r="5" t="1176" w="2135" /><ent r="5" t="1176" w="2155" /><ent r="5" t="1176" w="2159" /><ent r="5" t="1176" w="2180" /><ent r="5" t="1176" w="2184" /></phr></stem><stem n="subca"><phr n="subCA"><ent r="4" t="1176" w="2006" /><ent r="4" t="1176" w="2009" /><ent r="4" t="1176" w="2026" /><ent r="4" t="1176" w="2097" /><ent r="5" t="1176" w="2150" /></phr></stem><stem n="cert-with"><phr n="cert-with"><ent r="4" t="1176" w="2068" /></phr></stem><stem n="cert-with-chain"><phr n="cert-with-chain"><ent r="4" t="1176" w="2068" /></phr></stem><stem n="with-chain"><phr n="with-chain"><ent r="4" t="1176" w="2069" /></phr></stem><stem n="-with-chain.crt."><phr n="-with-chain.crt."><ent r="4" t="1176" w="2072" /><ent r="4" t="1176" w="2073" /></phr></stem><stem n="resembl"><phr n="resemble"><ent r="4" t="1176" w="2111" /></phr></stem><stem n="&lt;--"><phr n="&lt;--"><ent r="5" t="1176" w="2123" /><ent r="5" t="1176" w="2147" /><ent r="5" t="1176" w="2171" /></phr></stem><stem n="-sa5"><phr n="-sa5"><ent r="5" t="1176" w="2214" /><ent r="5" t="1176" w="2214" /></phr></stem><stem n="my-sa5"><phr n="my-sa5"><ent r="5" t="1176" w="2214" /></phr></stem><stem n="crl2pkcs7"><phr n="crl2pkcs7"><ent r="5" t="1176" w="2218" /><ent r="5" t="1176" w="2409" /></phr></stem><stem n="-nocrl"><phr n="-nocrl"><ent r="5" t="1176" w="2219" /><ent r="5" t="1176" w="2219" /><ent r="5" t="1176" w="2410" /><ent r="5" t="1176" w="2410" /></phr></stem><stem n="nocrl"><phr n="nocrl"><ent r="5" t="1176" w="2219" /><ent r="5" t="1176" w="2410" /></phr></stem><stem n="-certfil"><phr n="-certfile"><ent r="5" t="1176" w="2220" /><ent r="5" t="1176" w="2220" /><ent r="5" t="1176" w="2232" /><ent r="5" t="1176" w="2232" /><ent r="5" t="1176" w="2411" /><ent r="5" t="1176" w="2411" /><ent r="5" t="1176" w="2423" /><ent r="5" t="1176" w="2423" /></phr></stem><stem n="certfil"><phr n="certfile"><ent r="5" t="1176" w="2220" /><ent r="5" t="1176" w="2232" /><ent r="5" t="1176" w="2411" /><ent r="5" t="1176" w="2423" /></phr></stem><stem n="luna-manu"><phr n="Luna-manual"><ent r="5" t="1176" w="2222" /><ent r="5" t="1176" w="2228" /><ent r="5" t="1176" w="2413" /><ent r="5" t="1176" w="2419" /></phr></stem><stem n="luna-manual-chain"><phr n="Luna-manual-chain"><ent r="5" t="1176" w="2222" /><ent r="5" t="1176" w="2228" /><ent r="5" t="1176" w="2413" /><ent r="5" t="1176" w="2419" /></phr></stem><stem n="manual-chain"><phr n="manual-chain"><ent r="5" t="1176" w="2223" /><ent r="5" t="1176" w="2229" /><ent r="5" t="1176" w="2414" /><ent r="5" t="1176" w="2420" /></phr></stem><stem n="_luna-manual-chain.crt"><phr n="_Luna-manual-chain.crt"><ent r="5" t="1176" w="2225" /><ent r="5" t="1176" w="2416" /></phr></stem><stem n="_luna-manual-chain.p7b"><phr n="_Luna-manual-chain.p7b"><ent r="5" t="1176" w="2231" /><ent r="5" t="1176" w="2422" /></phr></stem><stem n=".p7b"><phr n=".p7b"><ent r="3" t="1176" w="2245" /></phr></stem><stem n="“cacerts”:"><phr n="“cacerts”:"><ent r="4" t="1176" w="2273" /></phr></stem><stem n="@myserver:~#"><phr n="@myserver:~#"><ent r="5" t="1176" w="2277" /></phr></stem><stem n="-trustcacert"><phr n="-trustcacerts"><ent r="5" t="1176" w="2279" /><ent r="5" t="1176" w="2279" /></phr></stem><stem n="trustcacert"><phr n="trustcacerts"><ent r="5" t="1176" w="2279" /></phr></stem><stem n="luna-keystor"><phr n="luna-keystores"><ent r="5" t="1176" w="2286" /></phr></stem><stem n="/home/ugo/luna-keystores/ugo_ca.crt"><phr n="/home/ugo/luna-keystores/Ugo_CA.crt"><ent r="5" t="1176" w="2290" /></phr></stem><stem n="java-6"><phr n="java-6"><ent r="5" t="1176" w="2293" /></phr></stem><stem n="java-6-sun"><phr n="java-6-sun"><ent r="5" t="1176" w="2293" /></phr></stem><stem n="6-sun"><phr n="6-sun"><ent r="5" t="1176" w="2294" /></phr></stem><stem n="/etc/java-6-sun/security/cacert"><phr n="/etc/java-6-sun/security/cacerts"><ent r="5" t="1176" w="2297" /></phr></stem><stem n="pem-encod"><phr n="PEM-encoded"><ent r="4" t="1176" w="2317" /></phr></stem><stem n="@myserver:~/tmp/$"><phr n="@myserver:~/tmp/$"><ent r="5" t="1176" w="2325" /><ent r="5" t="1176" w="2364" /><ent r="5" t="1176" w="2407" /></phr></stem><stem n="-client2.p7b"><phr n="-client2.p7b"><ent r="5" t="1176" w="2333" /><ent r="5" t="1176" w="2333" /></phr></stem><stem n="java-client2-pem"><phr n="java-client2-pem"><ent r="5" t="1176" w="2335" /></phr></stem><stem n="client2-pem"><phr n="client2-pem"><ent r="5" t="1176" w="2336" /></phr></stem><stem n="-client2-pem.p7b"><phr n="-client2-pem.p7b"><ent r="5" t="1176" w="2338" /><ent r="5" t="1176" w="2339" /></phr></stem><stem n="-print_cert"><phr n="-print_certs"><ent r="5" t="1176" w="2368" /><ent r="5" t="1176" w="2368" /></phr></stem><stem n="_ca.p7b"><phr n="_CA.p7b"><ent r="5" t="1176" w="2374" /></phr></stem><stem n="ca-p7"><phr n="CA-p7"><ent r="5" t="1176" w="2377" /></phr></stem><stem n="ca-p7-2"><phr n="CA-p7-2"><ent r="5" t="1176" w="2377" /></phr></stem><stem n="ca-p7-2-crt"><phr n="CA-p7-2-crt"><ent r="5" t="1176" w="2377" /></phr></stem><stem n="p7"><phr n="p7"><ent r="5" t="1176" w="2378" /></phr></stem><stem n="p7-2"><phr n="p7-2"><ent r="5" t="1176" w="2378" /></phr></stem><stem n="p7-2-crt"><phr n="p7-2-crt"><ent r="5" t="1176" w="2378" /></phr></stem><stem n="2-crt"><phr n="2-crt"><ent r="5" t="1176" w="2379" /></phr></stem><stem n="_ca-p7-2-crt.crt"><phr n="_CA-p7-2-crt.crt"><ent r="5" t="1176" w="2381" /></phr></stem><stem n="&quot;sun&quot;"><phr n="&quot;SUN&quot;"><ent r="3" t="1177" w="79" /></phr></stem><stem n=".safenetinc.luna.lunaslotmanager.getinstance().login(&quot;&lt;hsm"><phr n=".safenetinc.luna.LunaSlotManager.getInstance().login(&quot;&lt;HSM"><ent r="3" t="1177" w="118" /></phr></stem><stem n="&quot;);"><phr n="&quot;);"><ent r="3" t="1177" w="121" /></phr></stem><stem n=".security.provid"><phr n=".security.Provider"><ent r="3" t="1177" w="124" /></phr></stem><stem n=".safenetinc.luna.provider.lunaprovider();"><phr n=".safenetinc.luna.provider.LunaProvider();"><ent r="3" t="1177" w="132" /></phr></stem><stem n="removeprovid"><phr n="removeProvider"><ent r="3" t="1177" w="156" /></phr></stem><stem n="getnam"><phr n="getName"><ent r="3" t="1177" w="158" /></phr></stem><stem n=".security.security.removeprovider(provider.getname());"><phr n=".security.Security.removeProvider(provider.getName());"><ent r="3" t="1177" w="159" /></phr></stem><stem n="insertproviderat"><phr n="insertProviderAt"><ent r="3" t="1177" w="163" /></phr></stem><stem n=".security.security.insertproviderat(provider,"><phr n=".security.Security.insertProviderAt(provider,"><ent r="3" t="1177" w="165" /></phr></stem><stem n=".safenetinc.luna.lunaslotmanager.getinstance().logout();"><phr n=".safenetinc.luna.LunaSlotManager.getInstance().logout();"><ent r="3" t="1177" w="173" /></phr></stem><stem n="println"><phr n="println"><ent r="3" t="1177" w="180" /></phr></stem><stem n=".out.println(&quot;except"><phr n=".out.println(&quot;Exception"><ent r="3" t="1177" w="181" /></phr></stem><stem n="caught"><phr n="caught"><ent r="3" t="1177" w="182" /></phr></stem><stem n="getmessag"><phr n="getMessage"><ent r="3" t="1177" w="191" /></phr></stem><stem n=".getmessage());"><phr n=".getMessage());"><ent r="3" t="1177" w="192" /></phr></stem><stem n="crypt"><phr n="Crypt"><ent r="3" t="1179" w="27" /><ent r="3" t="1179" w="161" /><ent r="3" t="1179" w="272" /></phr></stem><stem n="cpacquirecontext"><phr n="CPAcquireContext"><ent r="3" t="1179" w="168" /></phr></stem><stem n="cpgetprovparam"><phr n="CPGetProvParam"><ent r="3" t="1179" w="170" /></phr></stem><stem n="cpsetprovparam"><phr n="CPSetProvParam"><ent r="3" t="1179" w="172" /></phr></stem><stem n="cpreleasecontext"><phr n="CPReleaseContext"><ent r="3" t="1179" w="174" /></phr></stem><stem n="cpderivekei"><phr n="CPDeriveKey"><ent r="3" t="1179" w="176" /></phr></stem><stem n="cpdestroykei"><phr n="CPDestroyKey"><ent r="3" t="1179" w="178" /></phr></stem><stem n="cpduplicatekei"><phr n="CPDuplicateKey"><ent r="3" t="1179" w="180" /></phr></stem><stem n="cpexportkei"><phr n="CPExportKey"><ent r="3" t="1179" w="182" /></phr></stem><stem n="cpgenkei"><phr n="CPGenKey"><ent r="3" t="1179" w="184" /></phr></stem><stem n="cpgenrandom"><phr n="CPGenRandom"><ent r="3" t="1179" w="186" /></phr></stem><stem n="cpgetkeyparam"><phr n="CPGetKeyParam"><ent r="3" t="1179" w="188" /></phr></stem><stem n="cpgetuserkei"><phr n="CPGetUserKey"><ent r="3" t="1179" w="190" /></phr></stem><stem n="cpimportkei"><phr n="CPImportKey"><ent r="3" t="1179" w="192" /></phr></stem><stem n="cpsetkeyparam"><phr n="CPSetKeyParam"><ent r="3" t="1179" w="194" /></phr></stem><stem n="cpdecrypt"><phr n="CPDecrypt"><ent r="3" t="1179" w="196" /></phr></stem><stem n="cpencrypt"><phr n="CPEncrypt"><ent r="3" t="1179" w="198" /></phr></stem><stem n="cpcreatehash"><phr n="CPCreateHash"><ent r="3" t="1179" w="200" /></phr></stem><stem n="cpdestroyhash"><phr n="CPDestroyHash"><ent r="3" t="1179" w="202" /></phr></stem><stem n="cpgethashparam"><phr n="CPGetHashParam"><ent r="3" t="1179" w="204" /></phr></stem><stem n="cphashdata"><phr n="CPHashData"><ent r="3" t="1179" w="206" /></phr></stem><stem n="cphashsessionkei"><phr n="CPHashSessionKey"><ent r="3" t="1179" w="208" /></phr></stem><stem n="cpsethashparam"><phr n="CPSetHashParam"><ent r="3" t="1179" w="210" /></phr></stem><stem n="cpsignhash"><phr n="CPSignHash"><ent r="3" t="1179" w="212" /><ent r="3" t="1179" w="238" /></phr></stem><stem n="cpverifysignatur"><phr n="CPVerifySignature"><ent r="3" t="1179" w="214" /><ent r="3" t="1179" w="217" /></phr></stem><stem n="msdn"><phr n="MSDN"><ent r="3" t="1179" w="259" /></phr></stem><stem n="(microsoft"><phr n="(Microsoft"><ent r="3" t="1179" w="260" /></phr></stem><stem n="calg"><phr n="CALG"><ent r="3" t="1179" w="292" /><ent r="3" t="1179" w="312" /><ent r="3" t="1179" w="351" /><ent r="3" t="1179" w="363" /><ent r="3" t="1179" w="375" /><ent r="3" t="1179" w="387" /><ent r="3" t="1179" w="397" /><ent r="3" t="1179" w="407" /><ent r="3" t="1179" w="416" /><ent r="3" t="1179" w="425" /><ent r="3" t="1179" w="431" /><ent r="3" t="1179" w="440" /><ent r="3" t="1179" w="449" /><ent r="3" t="1179" w="459" /><ent r="3" t="1179" w="469" /><ent r="3" t="1179" w="479" /><ent r="3" t="1179" w="489" /><ent r="3" t="1199" w="929" /><ent r="3" t="1199" w="933" /><ent r="3" t="1199" w="937" /><ent r="3" t="1199" w="940" /><ent r="3" t="1199" w="943" /><ent r="3" t="1199" w="946" /><ent r="3" t="1199" w="949" /><ent r="3" t="1199" w="953" /><ent r="3" t="1199" w="956" /><ent r="3" t="1199" w="959" /><ent r="3" t="1199" w="962" /><ent r="3" t="1199" w="965" /><ent r="3" t="1199" w="969" /><ent r="3" t="1199" w="973" /><ent r="3" t="1199" w="977" /><ent r="3" t="1199" w="980" /></phr></stem><stem n="_rsa_sign"><phr n="_RSA_SIGN"><ent r="3" t="1179" w="294" /><ent r="3" t="1199" w="931" /></phr></stem><stem n="[rsa"><phr n="[RSA"><ent r="3" t="1179" w="295" /><ent r="3" t="1179" w="315" /><ent r="3" t="1179" w="353" /><ent r="3" t="1179" w="365" /><ent r="3" t="1179" w="377" /></phr></stem><stem n="[256"><phr n="[256"><ent r="3" t="1179" w="297" /><ent r="3" t="1179" w="476" /></phr></stem><stem n="_rsa_keyx"><phr n="_RSA_KEYX"><ent r="3" t="1179" w="314" /><ent r="3" t="1199" w="935" /></phr></stem><stem n="keyx"><phr n="KEYX"><ent r="3" t="1179" w="314" /><ent r="3" t="1199" w="935" /></phr></stem><stem n="[256-"><phr n="[256-"><ent r="3" t="1179" w="318" /></phr></stem><stem n="256-"><phr n="256-"><ent r="3" t="1179" w="318" /></phr></stem><stem n="_rc2"><phr n="_RC2"><ent r="3" t="1179" w="352" /><ent r="3" t="1199" w="938" /></phr></stem><stem n="(block"><phr n="(block"><ent r="3" t="1179" w="357" /><ent r="3" t="1179" w="381" /><ent r="3" t="1179" w="392" /><ent r="3" t="1179" w="402" /><ent r="3" t="1179" w="411" /></phr></stem><stem n="[8"><phr n="[8"><ent r="3" t="1179" w="359" /><ent r="3" t="1179" w="371" /><ent r="3" t="1179" w="383" /></phr></stem><stem n="(stream"><phr n="(stream"><ent r="3" t="1179" w="369" /></phr></stem><stem n="_rc5"><phr n="_RC5"><ent r="3" t="1179" w="376" /><ent r="3" t="1199" w="944" /></phr></stem><stem n="[data"><phr n="[Data"><ent r="3" t="1179" w="389" /></phr></stem><stem n="[56"><phr n="[56"><ent r="3" t="1179" w="394" /></phr></stem><stem n="_3des_112"><phr n="_3DES_112"><ent r="3" t="1179" w="399" /><ent r="3" t="1199" w="951" /></phr></stem><stem n="[doubl"><phr n="[Double"><ent r="3" t="1179" w="400" /></phr></stem><stem n="[112"><phr n="[112"><ent r="3" t="1179" w="404" /></phr></stem><stem n="_3de"><phr n="_3DES"><ent r="3" t="1179" w="408" /><ent r="3" t="1199" w="954" /></phr></stem><stem n="[tripl"><phr n="[Triple"><ent r="3" t="1179" w="409" /></phr></stem><stem n="[168"><phr n="[168"><ent r="3" t="1179" w="413" /></phr></stem><stem n="_mac"><phr n="_MAC"><ent r="3" t="1179" w="417" /><ent r="3" t="1199" w="978" /></phr></stem><stem n="[messag"><phr n="[Message"><ent r="3" t="1179" w="418" /><ent r="3" t="1179" w="433" /><ent r="3" t="1179" w="442" /></phr></stem><stem n="_hmac"><phr n="_HMAC"><ent r="3" t="1179" w="426" /><ent r="3" t="1199" w="981" /></phr></stem><stem n="[hash-bas"><phr n="[Hash-based"><ent r="3" t="1179" w="427" /></phr></stem><stem n="hash-bas"><phr n="Hash-based"><ent r="3" t="1179" w="427" /></phr></stem><stem n="(md2)]"><phr n="(MD2)]"><ent r="3" t="1179" w="437" /></phr></stem><stem n="[128"><phr n="[128"><ent r="3" t="1179" w="437" /><ent r="3" t="1179" w="446" /></phr></stem><stem n="(md5)]"><phr n="(MD5)]"><ent r="3" t="1179" w="446" /></phr></stem><stem n="_sha"><phr n="_SHA"><ent r="3" t="1179" w="450" /><ent r="3" t="1199" w="963" /></phr></stem><stem n="[secur"><phr n="[Secure"><ent r="3" t="1179" w="451" /><ent r="3" t="1179" w="461" /><ent r="3" t="1179" w="471" /><ent r="3" t="1179" w="481" /><ent r="3" t="1179" w="491" /></phr></stem><stem n="(sha-1)]"><phr n="(SHA-1)]"><ent r="3" t="1179" w="456" /></phr></stem><stem n="[160"><phr n="[160"><ent r="3" t="1179" w="456" /></phr></stem><stem n="(sha-2)]"><phr n="(SHA-2)]"><ent r="3" t="1179" w="466" /><ent r="3" t="1179" w="476" /><ent r="3" t="1179" w="486" /><ent r="3" t="1179" w="496" /></phr></stem><stem n="[224"><phr n="[224"><ent r="3" t="1179" w="466" /></phr></stem><stem n="[384"><phr n="[384"><ent r="3" t="1179" w="486" /></phr></stem><stem n="[512"><phr n="[512"><ent r="3" t="1179" w="496" /></phr></stem><stem n="kp"><phr n="KP"><ent r="3" t="1179" w="519" /><ent r="3" t="1179" w="570" /><ent r="3" t="1179" w="574" /></phr></stem><stem n="_keylen"><phr n="_KEYLEN"><ent r="3" t="1179" w="521" /></phr></stem><stem n="keylen"><phr n="KEYLEN"><ent r="3" t="1179" w="521" /></phr></stem><stem n="salt"><phr n="salt"><ent r="3" t="1179" w="533" /><ent r="3" t="1179" w="548" /><ent r="3" t="1179" w="558" /><ent r="3" t="1179" w="571" /><ent r="3" t="1179" w="575" /></phr></stem><stem n="cryptgetkeyparam"><phr n="CryptGetKeyParam"><ent r="3" t="1179" w="569" /></phr></stem><stem n="cryptsetkeyparam"><phr n="CryptSetKeyParam"><ent r="3" t="1179" w="573" /></phr></stem><stem n="&quot;view"><phr n="&quot;Viewing"><ent r="65" t="1180" w="13" /><ent r="65" t="1180" w="22" /></phr></stem><stem n="html-format"><phr n="HTML-format"><ent r="3" t="1180" w="57" /></phr></stem><stem n="html5"><phr n="HTML5"><ent r="3" t="1180" w="63" /><ent r="3" t="1180" w="99" /></phr></stem><stem n="macintosh"><phr n="Macintosh"><ent r="3" t="1180" w="73" /></phr></stem><stem n="firefox"><phr n="Firefox"><ent r="3" t="1180" w="84" /></phr></stem><stem n="googl"><phr n="Google"><ent r="3" t="1180" w="88" /></phr></stem><stem n="chrome"><phr n="Chrome"><ent r="3" t="1180" w="89" /></phr></stem><stem n="hyperlink"><phr n="hyperlinked"><ent r="3" t="1180" w="123" /></phr></stem><stem n="autorun"><phr n="autorun"><ent r="3" t="1180" w="170" /></phr></stem><stem n="drive&gt;"><phr n="drive&gt;"><ent r="3" t="1180" w="183" /></phr></stem><stem n="_drive&gt;\index.htm."><phr n="_drive&gt;\index.htm."><ent r="3" t="1180" w="186" /></phr></stem><stem n="subtop"><phr n="subtopics"><ent r="3" t="1180" w="235" /><ent r="3" t="1180" w="431" /><ent r="3" t="1180" w="440" /><ent r="3" t="1180" w="461" /><ent r="3" t="1180" w="473" /></phr></stem><stem n="glossari"><phr n="Glossary"><ent r="3" t="1180" w="246" /></phr></stem><stem n="splash"><phr n="splash"><ent r="3" t="1180" w="262" /></phr></stem><stem n="collaps"><phr n="collapse"><ent r="3" t="1180" w="457" /></phr></stem><stem n="implicit"><phr n="implicit"><ent r="3" t="1180" w="517" /></phr></stem><stem n="“and”,"><phr n="“AND”,"><ent r="3" t="1180" w="519" /></phr></stem><stem n="/pdf_&lt;product&gt;"><phr n="/PDF_&lt;product&gt;"><ent r="3" t="1180" w="639" /></phr></stem><stem n="&lt;product&gt;"><phr n="&lt;product&gt;"><ent r="3" t="1180" w="639" /></phr></stem><stem n="clickabl"><phr n="Clickable"><ent r="72" t="1180" w="642" /><ent r="3" t="1180" w="656" /></phr></stem><stem n="cross-refer"><phr n="cross-references"><ent r="3" t="1180" w="646" /></phr><phr n="cross-reference"><ent r="3" t="1200" w="16" /><ent r="3" t="1200" w="30" /><ent r="3" t="1200" w="44" /></phr></stem><stem n="-references,"><phr n="-references,"><ent r="3" t="1180" w="648" /><ent r="3" t="1180" w="648" /></phr></stem><stem n="acrobat"><phr n="Acrobat"><ent r="3" t="1180" w="686" /><ent r="3" t="1180" w="707" /><ent r="3" t="1180" w="732" /></phr></stem><stem n="adob"><phr n="Adobe"><ent r="3" t="1180" w="731" /></phr></stem><stem n="photo"><phr n="photos"><ent r="3" t="1181" w="32" /></phr></stem><stem n="line-draw"><phr n="line-drawings"><ent r="3" t="1181" w="36" /></phr></stem><stem n="-drawings."><phr n="-drawings."><ent r="3" t="1181" w="38" /><ent r="3" t="1181" w="38" /></phr></stem><stem n="&quot;hot-swap&quot;-cap"><phr n="&quot;hot-swap&quot;-capable"><ent r="3" t="1181" w="50" /></phr></stem><stem n="tone"><phr n="tone"><ent r="3" t="1181" w="130" /></phr></stem><stem n="squeez"><phr n="Squeeze"><ent r="3" t="1181" w="183" /></phr></stem><stem n=".support"><phr n=".Support"><ent r="3" t="1181" w="203" /></phr></stem><stem n="expel"><phr n="expelled"><ent r="3" t="1181" w="350" /></phr></stem><stem n="heat"><phr n="heat"><ent r="3" t="1181" w="357" /></phr></stem><stem n="tandem"><phr n="tandem"><ent r="3" t="1181" w="360" /></phr></stem><stem n="intak"><phr n="intake"><ent r="3" t="1181" w="394" /></phr></stem><stem n="pollut"><phr n="pollutants"><ent r="3" t="1181" w="400" /></phr></stem><stem n="-than-id"><phr n="-than-ideal"><ent r="3" t="1181" w="411" /><ent r="3" t="1181" w="412" /></phr></stem><stem n="less-than-id"><phr n="less-than-ideal"><ent r="3" t="1181" w="411" /></phr></stem><stem n="than-id"><phr n="than-ideal"><ent r="3" t="1181" w="412" /></phr></stem><stem n="dirti"><phr n="dirty"><ent r="3" t="1181" w="419" /><ent r="3" t="1181" w="628" /></phr></stem><stem n="uncov"><phr n="uncover"><ent r="3" t="1181" w="504" /></phr></stem><stem n="-grid"><phr n="-grid"><ent r="3" t="1181" w="532" /><ent r="3" t="1181" w="532" /></phr></stem><stem n="open-grid"><phr n="open-grid"><ent r="3" t="1181" w="532" /></phr></stem><stem n="grid"><phr n="grid"><ent r="3" t="1181" w="533" /></phr></stem><stem n="knurled-knob"><phr n="knurled-knob"><ent r="3" t="1181" w="559" /></phr></stem><stem n="-knob."><phr n="-knob."><ent r="3" t="1181" w="561" /><ent r="3" t="1181" w="561" /></phr></stem><stem n="(twist"><phr n="(twist"><ent r="3" t="1181" w="577" /></phr></stem><stem n="-clockwise)."><phr n="-clockwise)."><ent r="3" t="1181" w="580" /><ent r="3" t="1181" w="580" /></phr></stem><stem n="-dry"><phr n="-dry"><ent r="3" t="1181" w="636" /><ent r="3" t="1181" w="636" /></phr></stem><stem n="air-dri"><phr n="air-dry"><ent r="3" t="1181" w="636" /></phr></stem><stem n="blunt-end"><phr n="blunt-end"><ent r="3" t="1181" w="669" /></phr></stem><stem n="/replaceable,"><phr n="/replaceable,"><ent r="3" t="1181" w="695" /></phr></stem><stem n="[new]"><phr n="[new]"><ent r="3" t="1181" w="909" /></phr></stem><stem n="snugli"><phr n="snugly"><ent r="3" t="1181" w="943" /></phr></stem><stem n="hot-swapp"><phr n="hot-swappable"><ent r="3" t="1181" w="1068" /></phr></stem><stem n="swappabl"><phr n="swappable"><ent r="3" t="1181" w="1069" /></phr></stem><stem n="&quot;hot-swappable&quot;"><phr n="&quot;hot-swappable&quot;"><ent r="3" t="1181" w="1070" /></phr></stem><stem n="-time-token,"><phr n="-time-token,"><ent r="3" t="1183" w="46" /><ent r="3" t="1183" w="47" /></phr></stem><stem n="notlunasp"><phr n="notLunaSP"><ent r="100" t="1184" w="11" /><ent r="100" t="1185" w="12" /></phr></stem><stem n=".notlunasp,primary.notpci"><phr n=".notLunaSP,Primary.notPCI"><ent r="100" t="1184" w="13" /><ent r="100" t="1185" w="14" /></phr></stem><stem n="notpci"><phr n="notPCI"><ent r="100" t="1184" w="13" /><ent r="100" t="1185" w="14" /></phr></stem><stem n="/daemon."><phr n="/daemon."><ent r="3" t="1184" w="45" /></phr></stem><stem n="1867"><phr n="1867"><ent r="3" t="1184" w="107" /></phr></stem><stem n="/ip."><phr n="/IP."><ent r="3" t="1184" w="144" /></phr></stem><stem n="/affect"><phr n="/affects"><ent r="3" t="1184" w="257" /></phr></stem><stem n="“attempt"><phr n="“Attempting"><ent r="3" t="1184" w="357" /></phr></stem><stem n="].if"><phr n="].If"><ent r="3" t="1184" w="360" /></phr></stem><stem n="“down”."><phr n="“down”."><ent r="3" t="1184" w="394" /></phr></stem><stem n="(client"><phr n="(Client"><ent r="3" t="1184" w="430" /></phr></stem><stem n="-ottexpir"><phr n="-ottExpir"><ent r="4" t="1184" w="530" /><ent r="4" t="1184" w="530" /></phr></stem><stem n="ottexpir"><phr n="ottExpir"><ent r="4" t="1184" w="530" /></phr></stem><stem n="(vm)."><phr n="(VM)."><ent r="3" t="1185" w="75" /></phr></stem><stem n="unprotect"><phr n="unprotected"><ent r="3" t="1185" w="76" /></phr></stem><stem n="-refresh"><phr n="-refresh"><ent r="3" t="1185" w="361" /><ent r="3" t="1185" w="361" /></phr></stem><stem n="@lunasa:server.pem"><phr n="@LunaSA:server.pem"><ent r="4" t="1186" w="85" /></phr></stem><stem n="@lunasa’"><phr n="@LunaSA’s"><ent r="4" t="1186" w="89" /><ent r="4" t="1187" w="326" /></phr></stem><stem n="1164"><phr n="1164"><ent r="4" t="1186" w="95" /><ent r="4" t="1186" w="283" /></phr></stem><stem n=".1kb/"><phr n=".1KB/s"><ent r="4" t="1186" w="98" /><ent r="4" t="1186" w="286" /></phr></stem><stem n="(specifi"><phr n="(specifying"><ent r="82" t="1186" w="111" /><ent r="82" t="1187" w="124" /></phr></stem><stem n="&lt;sahostnam"><phr n="&lt;SAhostname"><ent r="3" t="1186" w="140" /><ent r="3" t="1186" w="258" /><ent r="3" t="1186" w="520" /><ent r="3" t="1186" w="642" /><ent r="3" t="1187" w="300" /><ent r="3" t="1187" w="575" /><ent r="3" t="1187" w="678" /></phr></stem><stem n="&lt;sahostname-or"><phr n="&lt;SAhostname-or"><ent r="3" t="1186" w="140" /><ent r="3" t="1186" w="258" /><ent r="3" t="1186" w="520" /><ent r="3" t="1186" w="642" /><ent r="3" t="1187" w="300" /><ent r="3" t="1187" w="575" /><ent r="3" t="1187" w="678" /></phr></stem><stem n="&lt;sahostname-or-ipaddress&gt;"><phr n="&lt;SAhostname-or-IPaddress&gt;"><ent r="3" t="1186" w="140" /><ent r="3" t="1186" w="258" /><ent r="3" t="1186" w="520" /><ent r="3" t="1186" w="642" /><ent r="3" t="1187" w="300" /><ent r="3" t="1187" w="575" /></phr></stem><stem n="–htl"><phr n="–htl"><ent r="3" t="1186" w="146" /><ent r="4" t="1186" w="157" /><ent r="4" t="1187" w="179" /></phr></stem></index>