<?xml version="1.0" encoding="utf-8"?><index><stem n="btmp-20110311-0402"><phr n="btmp-20110311-0402"><ent r="3" t="760" w="226" /></phr></stem><stem n="20110311"><phr n="20110311"><ent r="3" t="760" w="227" /><ent r="3" t="760" w="332" /><ent r="3" t="760" w="564" /><ent r="3" t="760" w="761" /><ent r="3" t="760" w="1180" /><ent r="3" t="760" w="1371" /></phr></stem><stem n="20110311-0402"><phr n="20110311-0402"><ent r="3" t="760" w="227" /><ent r="3" t="760" w="332" /><ent r="3" t="760" w="564" /><ent r="3" t="760" w="761" /><ent r="3" t="760" w="1180" /><ent r="3" t="760" w="1371" /></phr></stem><stem n="4992"><phr n="4992"><ent r="3" t="760" w="229" /></phr></stem><stem n="-20110402-0402"><phr n="-20110402-0402"><ent r="3" t="760" w="234" /><ent r="3" t="760" w="235" /><ent r="3" t="760" w="339" /><ent r="3" t="760" w="340" /><ent r="3" t="760" w="571" /><ent r="3" t="760" w="572" /><ent r="3" t="760" w="768" /><ent r="3" t="760" w="769" /><ent r="3" t="760" w="1187" /><ent r="3" t="760" w="1188" /><ent r="3" t="760" w="1378" /><ent r="3" t="760" w="1379" /></phr></stem><stem n="btmp-20110402"><phr n="btmp-20110402"><ent r="3" t="760" w="234" /></phr></stem><stem n="btmp-20110402-0402"><phr n="btmp-20110402-0402"><ent r="3" t="760" w="234" /></phr></stem><stem n="20110402"><phr n="20110402"><ent r="3" t="760" w="235" /><ent r="3" t="760" w="340" /><ent r="3" t="760" w="572" /><ent r="3" t="760" w="769" /><ent r="3" t="760" w="1188" /><ent r="3" t="760" w="1379" /></phr></stem><stem n="20110402-0402"><phr n="20110402-0402"><ent r="3" t="760" w="235" /><ent r="3" t="760" w="340" /><ent r="3" t="760" w="572" /><ent r="3" t="760" w="769" /><ent r="3" t="760" w="1188" /><ent r="3" t="760" w="1379" /></phr></stem><stem n="8064"><phr n="8064"><ent r="3" t="760" w="237" /></phr></stem><stem n="-20110501-0402"><phr n="-20110501-0402"><ent r="3" t="760" w="242" /><ent r="3" t="760" w="243" /><ent r="3" t="760" w="379" /><ent r="3" t="760" w="380" /><ent r="3" t="760" w="611" /><ent r="3" t="760" w="612" /><ent r="3" t="760" w="808" /><ent r="3" t="760" w="809" /><ent r="3" t="760" w="1227" /><ent r="3" t="760" w="1228" /><ent r="3" t="760" w="1418" /><ent r="3" t="760" w="1419" /></phr></stem><stem n="btmp-20110501"><phr n="btmp-20110501"><ent r="3" t="760" w="242" /></phr></stem><stem n="btmp-20110501-0402"><phr n="btmp-20110501-0402"><ent r="3" t="760" w="242" /></phr></stem><stem n="20110501"><phr n="20110501"><ent r="3" t="760" w="243" /><ent r="3" t="760" w="380" /><ent r="3" t="760" w="612" /><ent r="3" t="760" w="809" /><ent r="3" t="760" w="969" /><ent r="3" t="760" w="1228" /><ent r="3" t="760" w="1419" /></phr></stem><stem n="20110501-0402"><phr n="20110501-0402"><ent r="3" t="760" w="243" /><ent r="3" t="760" w="380" /><ent r="3" t="760" w="612" /><ent r="3" t="760" w="809" /><ent r="3" t="760" w="969" /><ent r="3" t="760" w="1228" /><ent r="3" t="760" w="1419" /></phr></stem><stem n="-20110714-0402"><phr n="-20110714-0402"><ent r="3" t="760" w="250" /><ent r="3" t="760" w="251" /><ent r="3" t="760" w="403" /><ent r="3" t="760" w="404" /><ent r="3" t="760" w="635" /><ent r="3" t="760" w="636" /><ent r="3" t="760" w="832" /><ent r="3" t="760" w="833" /><ent r="3" t="760" w="1251" /><ent r="3" t="760" w="1252" /><ent r="3" t="760" w="1442" /><ent r="3" t="760" w="1443" /></phr></stem><stem n="btmp-20110714"><phr n="btmp-20110714"><ent r="3" t="760" w="250" /></phr></stem><stem n="btmp-20110714-0402"><phr n="btmp-20110714-0402"><ent r="3" t="760" w="250" /></phr></stem><stem n="20110714"><phr n="20110714"><ent r="3" t="760" w="251" /><ent r="3" t="760" w="404" /><ent r="3" t="760" w="636" /><ent r="3" t="760" w="833" /><ent r="3" t="760" w="999" /><ent r="3" t="760" w="1252" /><ent r="3" t="760" w="1443" /></phr></stem><stem n="20110714-0402"><phr n="20110714-0402"><ent r="3" t="760" w="251" /><ent r="3" t="760" w="404" /><ent r="3" t="760" w="636" /><ent r="3" t="760" w="833" /><ent r="3" t="760" w="999" /><ent r="3" t="760" w="1252" /><ent r="3" t="760" w="1443" /></phr></stem><stem n="btmp-2012"><phr n="btmp-2012"><ent r="3" t="760" w="258" /></phr></stem><stem n="btmp-2012-02"><phr n="btmp-2012-02"><ent r="3" t="760" w="258" /></phr></stem><stem n="btmp-2012-02-22"><phr n="btmp-2012-02-22"><ent r="3" t="760" w="258" /></phr></stem><stem n="768"><phr n="768"><ent r="3" t="760" w="262" /></phr></stem><stem n=":07"><phr n=":07"><ent r="3" t="760" w="266" /></phr></stem><stem n="cron-20101213"><phr n="cron-20101213"><ent r="3" t="760" w="275" /></phr></stem><stem n="cron-20101213-0402"><phr n="cron-20101213-0402"><ent r="3" t="760" w="275" /></phr></stem><stem n="-20101219-0402"><phr n="-20101219-0402"><ent r="3" t="760" w="283" /><ent r="3" t="760" w="284" /><ent r="3" t="760" w="515" /><ent r="3" t="760" w="516" /><ent r="3" t="760" w="712" /><ent r="3" t="760" w="713" /><ent r="3" t="760" w="1131" /><ent r="3" t="760" w="1132" /><ent r="3" t="760" w="1322" /><ent r="3" t="760" w="1323" /></phr></stem><stem n="cron-20101219"><phr n="cron-20101219"><ent r="3" t="760" w="283" /></phr></stem><stem n="cron-20101219-0402"><phr n="cron-20101219-0402"><ent r="3" t="760" w="283" /></phr></stem><stem n="20101219"><phr n="20101219"><ent r="3" t="760" w="284" /><ent r="3" t="760" w="516" /><ent r="3" t="760" w="713" /><ent r="3" t="760" w="1132" /><ent r="3" t="760" w="1323" /></phr></stem><stem n="20101219-0402"><phr n="20101219-0402"><ent r="3" t="760" w="284" /><ent r="3" t="760" w="516" /><ent r="3" t="760" w="713" /><ent r="3" t="760" w="1132" /><ent r="3" t="760" w="1323" /></phr></stem><stem n="690"><phr n="690"><ent r="3" t="760" w="286" /></phr></stem><stem n="-20101226-1432"><phr n="-20101226-1432"><ent r="3" t="760" w="291" /><ent r="3" t="760" w="292" /><ent r="3" t="760" w="523" /><ent r="3" t="760" w="524" /><ent r="3" t="760" w="720" /><ent r="3" t="760" w="721" /><ent r="3" t="760" w="1139" /><ent r="3" t="760" w="1140" /><ent r="3" t="760" w="1330" /><ent r="3" t="760" w="1331" /></phr></stem><stem n="cron-20101226"><phr n="cron-20101226"><ent r="3" t="760" w="291" /></phr></stem><stem n="cron-20101226-1432"><phr n="cron-20101226-1432"><ent r="3" t="760" w="291" /></phr></stem><stem n="20101226"><phr n="20101226"><ent r="3" t="760" w="292" /><ent r="3" t="760" w="524" /><ent r="3" t="760" w="721" /><ent r="3" t="760" w="1140" /><ent r="3" t="760" w="1331" /></phr></stem><stem n="20101226-1432"><phr n="20101226-1432"><ent r="3" t="760" w="292" /><ent r="3" t="760" w="524" /><ent r="3" t="760" w="721" /><ent r="3" t="760" w="1140" /><ent r="3" t="760" w="1331" /></phr></stem><stem n="1432"><phr n="1432"><ent r="3" t="760" w="293" /><ent r="3" t="760" w="525" /><ent r="3" t="760" w="722" /><ent r="3" t="760" w="1141" /><ent r="3" t="760" w="1332" /></phr></stem><stem n="921"><phr n="921"><ent r="3" t="760" w="294" /></phr></stem><stem n="-20110102-0402"><phr n="-20110102-0402"><ent r="3" t="760" w="299" /><ent r="3" t="760" w="300" /><ent r="3" t="760" w="531" /><ent r="3" t="760" w="532" /><ent r="3" t="760" w="728" /><ent r="3" t="760" w="729" /><ent r="3" t="760" w="1147" /><ent r="3" t="760" w="1148" /><ent r="3" t="760" w="1338" /><ent r="3" t="760" w="1339" /></phr></stem><stem n="cron-20110102"><phr n="cron-20110102"><ent r="3" t="760" w="299" /></phr></stem><stem n="cron-20110102-0402"><phr n="cron-20110102-0402"><ent r="3" t="760" w="299" /></phr></stem><stem n="20110102"><phr n="20110102"><ent r="3" t="760" w="300" /><ent r="3" t="760" w="532" /><ent r="3" t="760" w="729" /><ent r="3" t="760" w="1148" /><ent r="3" t="760" w="1339" /></phr></stem><stem n="20110102-0402"><phr n="20110102-0402"><ent r="3" t="760" w="300" /><ent r="3" t="760" w="532" /><ent r="3" t="760" w="729" /><ent r="3" t="760" w="1148" /><ent r="3" t="760" w="1339" /></phr></stem><stem n="1037"><phr n="1037"><ent r="3" t="760" w="302" /></phr></stem><stem n="-20110109-0402"><phr n="-20110109-0402"><ent r="3" t="760" w="307" /><ent r="3" t="760" w="308" /><ent r="3" t="760" w="539" /><ent r="3" t="760" w="540" /><ent r="3" t="760" w="736" /><ent r="3" t="760" w="737" /><ent r="3" t="760" w="1155" /><ent r="3" t="760" w="1156" /><ent r="3" t="760" w="1346" /><ent r="3" t="760" w="1347" /></phr></stem><stem n="cron-20110109"><phr n="cron-20110109"><ent r="3" t="760" w="307" /></phr></stem><stem n="cron-20110109-0402"><phr n="cron-20110109-0402"><ent r="3" t="760" w="307" /></phr></stem><stem n="20110109"><phr n="20110109"><ent r="3" t="760" w="308" /><ent r="3" t="760" w="540" /><ent r="3" t="760" w="737" /><ent r="3" t="760" w="1156" /><ent r="3" t="760" w="1347" /></phr></stem><stem n="20110109-0402"><phr n="20110109-0402"><ent r="3" t="760" w="308" /><ent r="3" t="760" w="540" /><ent r="3" t="760" w="737" /><ent r="3" t="760" w="1156" /><ent r="3" t="760" w="1347" /></phr></stem><stem n="918"><phr n="918"><ent r="3" t="760" w="310" /></phr></stem><stem n="-20110116-0402"><phr n="-20110116-0402"><ent r="3" t="760" w="315" /><ent r="3" t="760" w="316" /><ent r="3" t="760" w="547" /><ent r="3" t="760" w="548" /><ent r="3" t="760" w="744" /><ent r="3" t="760" w="745" /><ent r="3" t="760" w="1163" /><ent r="3" t="760" w="1164" /><ent r="3" t="760" w="1354" /><ent r="3" t="760" w="1355" /></phr></stem><stem n="cron-20110116"><phr n="cron-20110116"><ent r="3" t="760" w="315" /></phr></stem><stem n="cron-20110116-0402"><phr n="cron-20110116-0402"><ent r="3" t="760" w="315" /></phr></stem><stem n="20110116"><phr n="20110116"><ent r="3" t="760" w="316" /><ent r="3" t="760" w="548" /><ent r="3" t="760" w="745" /><ent r="3" t="760" w="1164" /><ent r="3" t="760" w="1355" /></phr></stem><stem n="20110116-0402"><phr n="20110116-0402"><ent r="3" t="760" w="316" /><ent r="3" t="760" w="548" /><ent r="3" t="760" w="745" /><ent r="3" t="760" w="1164" /><ent r="3" t="760" w="1355" /></phr></stem><stem n="917"><phr n="917"><ent r="3" t="760" w="318" /></phr></stem><stem n="-20110123-0402"><phr n="-20110123-0402"><ent r="3" t="760" w="323" /><ent r="3" t="760" w="324" /><ent r="3" t="760" w="555" /><ent r="3" t="760" w="556" /><ent r="3" t="760" w="752" /><ent r="3" t="760" w="753" /><ent r="3" t="760" w="1171" /><ent r="3" t="760" w="1172" /><ent r="3" t="760" w="1362" /><ent r="3" t="760" w="1363" /></phr></stem><stem n="cron-20110123"><phr n="cron-20110123"><ent r="3" t="760" w="323" /></phr></stem><stem n="cron-20110123-0402"><phr n="cron-20110123-0402"><ent r="3" t="760" w="323" /></phr></stem><stem n="20110123"><phr n="20110123"><ent r="3" t="760" w="324" /><ent r="3" t="760" w="556" /><ent r="3" t="760" w="753" /><ent r="3" t="760" w="1172" /><ent r="3" t="760" w="1363" /></phr></stem><stem n="20110123-0402"><phr n="20110123-0402"><ent r="3" t="760" w="324" /><ent r="3" t="760" w="556" /><ent r="3" t="760" w="753" /><ent r="3" t="760" w="1172" /><ent r="3" t="760" w="1363" /></phr></stem><stem n="920"><phr n="920"><ent r="3" t="760" w="326" /></phr></stem><stem n="cron-20110311"><phr n="cron-20110311"><ent r="3" t="760" w="331" /></phr></stem><stem n="cron-20110311-0402"><phr n="cron-20110311-0402"><ent r="3" t="760" w="331" /></phr></stem><stem n="575"><phr n="575"><ent r="3" t="760" w="334" /></phr></stem><stem n="cron-20110402"><phr n="cron-20110402"><ent r="3" t="760" w="339" /></phr></stem><stem n="cron-20110402-0402"><phr n="cron-20110402-0402"><ent r="3" t="760" w="339" /></phr></stem><stem n="-20110403-0402"><phr n="-20110403-0402"><ent r="3" t="760" w="347" /><ent r="3" t="760" w="348" /><ent r="3" t="760" w="776" /><ent r="3" t="760" w="777" /><ent r="3" t="760" w="1195" /><ent r="3" t="760" w="1196" /></phr></stem><stem n="cron-20110403"><phr n="cron-20110403"><ent r="3" t="760" w="347" /></phr></stem><stem n="cron-20110403-0402"><phr n="cron-20110403-0402"><ent r="3" t="760" w="347" /></phr></stem><stem n="20110403"><phr n="20110403"><ent r="3" t="760" w="348" /><ent r="3" t="760" w="777" /><ent r="3" t="760" w="1196" /></phr></stem><stem n="20110403-0402"><phr n="20110403-0402"><ent r="3" t="760" w="348" /><ent r="3" t="760" w="777" /><ent r="3" t="760" w="1196" /></phr></stem><stem n="-20110410-0402"><phr n="-20110410-0402"><ent r="3" t="760" w="355" /><ent r="3" t="760" w="356" /><ent r="3" t="760" w="587" /><ent r="3" t="760" w="588" /><ent r="3" t="760" w="784" /><ent r="3" t="760" w="785" /><ent r="3" t="760" w="1203" /><ent r="3" t="760" w="1204" /><ent r="3" t="760" w="1394" /><ent r="3" t="760" w="1395" /></phr></stem><stem n="cron-20110410"><phr n="cron-20110410"><ent r="3" t="760" w="355" /></phr></stem><stem n="cron-20110410-0402"><phr n="cron-20110410-0402"><ent r="3" t="760" w="355" /></phr></stem><stem n="20110410"><phr n="20110410"><ent r="3" t="760" w="356" /><ent r="3" t="760" w="588" /><ent r="3" t="760" w="785" /><ent r="3" t="760" w="939" /><ent r="3" t="760" w="1204" /><ent r="3" t="760" w="1395" /></phr></stem><stem n="20110410-0402"><phr n="20110410-0402"><ent r="3" t="760" w="356" /><ent r="3" t="760" w="588" /><ent r="3" t="760" w="785" /><ent r="3" t="760" w="939" /><ent r="3" t="760" w="1204" /><ent r="3" t="760" w="1395" /></phr></stem><stem n="862"><phr n="862"><ent r="3" t="760" w="358" /><ent r="3" t="760" w="366" /></phr></stem><stem n="-20110417-0402"><phr n="-20110417-0402"><ent r="3" t="760" w="363" /><ent r="3" t="760" w="364" /><ent r="3" t="760" w="595" /><ent r="3" t="760" w="596" /><ent r="3" t="760" w="792" /><ent r="3" t="760" w="793" /><ent r="3" t="760" w="1211" /><ent r="3" t="760" w="1212" /><ent r="3" t="760" w="1402" /><ent r="3" t="760" w="1403" /></phr></stem><stem n="cron-20110417"><phr n="cron-20110417"><ent r="3" t="760" w="363" /></phr></stem><stem n="cron-20110417-0402"><phr n="cron-20110417-0402"><ent r="3" t="760" w="363" /></phr></stem><stem n="20110417"><phr n="20110417"><ent r="3" t="760" w="364" /><ent r="3" t="760" w="596" /><ent r="3" t="760" w="793" /><ent r="3" t="760" w="949" /><ent r="3" t="760" w="1212" /><ent r="3" t="760" w="1403" /></phr></stem><stem n="20110417-0402"><phr n="20110417-0402"><ent r="3" t="760" w="364" /><ent r="3" t="760" w="596" /><ent r="3" t="760" w="793" /><ent r="3" t="760" w="949" /><ent r="3" t="760" w="1212" /><ent r="3" t="760" w="1403" /></phr></stem><stem n="-20110424-0402"><phr n="-20110424-0402"><ent r="3" t="760" w="371" /><ent r="3" t="760" w="372" /><ent r="3" t="760" w="603" /><ent r="3" t="760" w="604" /><ent r="3" t="760" w="800" /><ent r="3" t="760" w="801" /><ent r="3" t="760" w="1219" /><ent r="3" t="760" w="1220" /><ent r="3" t="760" w="1410" /><ent r="3" t="760" w="1411" /></phr></stem><stem n="cron-20110424"><phr n="cron-20110424"><ent r="3" t="760" w="371" /></phr></stem><stem n="cron-20110424-0402"><phr n="cron-20110424-0402"><ent r="3" t="760" w="371" /></phr></stem><stem n="20110424"><phr n="20110424"><ent r="3" t="760" w="372" /><ent r="3" t="760" w="604" /><ent r="3" t="760" w="801" /><ent r="3" t="760" w="959" /><ent r="3" t="760" w="1220" /><ent r="3" t="760" w="1411" /></phr></stem><stem n="20110424-0402"><phr n="20110424-0402"><ent r="3" t="760" w="372" /><ent r="3" t="760" w="604" /><ent r="3" t="760" w="801" /><ent r="3" t="760" w="959" /><ent r="3" t="760" w="1220" /><ent r="3" t="760" w="1411" /></phr></stem><stem n="861"><phr n="861"><ent r="3" t="760" w="374" /></phr></stem><stem n="cron-20110501"><phr n="cron-20110501"><ent r="3" t="760" w="379" /></phr></stem><stem n="cron-20110501-0402"><phr n="cron-20110501-0402"><ent r="3" t="760" w="379" /></phr></stem><stem n="-20110508-0102"><phr n="-20110508-0102"><ent r="3" t="760" w="387" /><ent r="3" t="760" w="388" /><ent r="3" t="760" w="619" /><ent r="3" t="760" w="620" /><ent r="3" t="760" w="816" /><ent r="3" t="760" w="817" /><ent r="3" t="760" w="1235" /><ent r="3" t="760" w="1236" /><ent r="3" t="760" w="1426" /><ent r="3" t="760" w="1427" /></phr></stem><stem n="cron-20110508"><phr n="cron-20110508"><ent r="3" t="760" w="387" /></phr></stem><stem n="cron-20110508-0102"><phr n="cron-20110508-0102"><ent r="3" t="760" w="387" /></phr></stem><stem n="20110508"><phr n="20110508"><ent r="3" t="760" w="388" /><ent r="3" t="760" w="620" /><ent r="3" t="760" w="817" /><ent r="3" t="760" w="979" /><ent r="3" t="760" w="1236" /><ent r="3" t="760" w="1427" /></phr></stem><stem n="20110508-0102"><phr n="20110508-0102"><ent r="3" t="760" w="388" /><ent r="3" t="760" w="620" /><ent r="3" t="760" w="817" /><ent r="3" t="760" w="979" /><ent r="3" t="760" w="1236" /><ent r="3" t="760" w="1427" /></phr></stem><stem n="0102"><phr n="0102"><ent r="3" t="760" w="389" /><ent r="3" t="760" w="621" /><ent r="3" t="760" w="818" /><ent r="3" t="760" w="980" /><ent r="3" t="760" w="1237" /><ent r="3" t="760" w="1428" /></phr></stem><stem n="972"><phr n="972"><ent r="3" t="760" w="390" /><ent r="3" t="760" w="423" /></phr></stem><stem n="cron-20110516"><phr n="cron-20110516"><ent r="3" t="760" w="395" /></phr></stem><stem n="cron-20110516-0833"><phr n="cron-20110516-0833"><ent r="3" t="760" w="395" /></phr></stem><stem n="646"><phr n="646"><ent r="3" t="760" w="398" /></phr></stem><stem n="cron-20110714"><phr n="cron-20110714"><ent r="3" t="760" w="403" /></phr></stem><stem n="cron-20110714-0402"><phr n="cron-20110714-0402"><ent r="3" t="760" w="403" /></phr></stem><stem n="432"><phr n="432"><ent r="3" t="760" w="406" /><ent r="3" t="760" w="453" /></phr></stem><stem n="-20110823-0402"><phr n="-20110823-0402"><ent r="3" t="760" w="411" /><ent r="3" t="760" w="412" /><ent r="3" t="760" w="643" /><ent r="3" t="760" w="644" /><ent r="3" t="760" w="840" /><ent r="3" t="760" w="841" /><ent r="3" t="760" w="1259" /><ent r="3" t="760" w="1260" /><ent r="3" t="760" w="1450" /><ent r="3" t="760" w="1451" /></phr></stem><stem n="cron-20110823"><phr n="cron-20110823"><ent r="3" t="760" w="411" /></phr></stem><stem n="cron-20110823-0402"><phr n="cron-20110823-0402"><ent r="3" t="760" w="411" /></phr></stem><stem n="20110823"><phr n="20110823"><ent r="3" t="760" w="412" /><ent r="3" t="760" w="644" /><ent r="3" t="760" w="841" /><ent r="3" t="760" w="1260" /><ent r="3" t="760" w="1451" /></phr></stem><stem n="20110823-0402"><phr n="20110823-0402"><ent r="3" t="760" w="412" /><ent r="3" t="760" w="644" /><ent r="3" t="760" w="841" /><ent r="3" t="760" w="1260" /><ent r="3" t="760" w="1451" /></phr></stem><stem n="-2012-02-05"><phr n="-2012-02-05"><ent r="3" t="760" w="419" /><ent r="3" t="760" w="421" /><ent r="3" t="760" w="651" /><ent r="3" t="760" w="653" /><ent r="3" t="760" w="848" /><ent r="3" t="760" w="850" /><ent r="3" t="760" w="1267" /><ent r="3" t="760" w="1269" /><ent r="3" t="760" w="1458" /><ent r="3" t="760" w="1460" /></phr></stem><stem n="cron-2012"><phr n="cron-2012"><ent r="3" t="760" w="419" /><ent r="3" t="760" w="429" /><ent r="3" t="760" w="439" /><ent r="3" t="760" w="449" /></phr></stem><stem n="cron-2012-02"><phr n="cron-2012-02"><ent r="3" t="760" w="419" /><ent r="3" t="760" w="429" /><ent r="3" t="760" w="439" /><ent r="3" t="760" w="449" /></phr></stem><stem n="cron-2012-02-05"><phr n="cron-2012-02-05"><ent r="3" t="760" w="419" /></phr></stem><stem n="2012-02-05"><phr n="2012-02-05"><ent r="3" t="760" w="420" /><ent r="3" t="760" w="652" /><ent r="3" t="760" w="849" /><ent r="3" t="760" w="1268" /><ent r="3" t="760" w="1459" /></phr></stem><stem n="02-05"><phr n="02-05"><ent r="3" t="760" w="421" /><ent r="3" t="760" w="653" /><ent r="3" t="760" w="850" /><ent r="3" t="760" w="1269" /><ent r="3" t="760" w="1460" /></phr></stem><stem n=":02"><phr n=":02"><ent r="3" t="760" w="427" /><ent r="3" t="760" w="437" /><ent r="3" t="760" w="447" /><ent r="3" t="760" w="457" /><ent r="3" t="760" w="479" /><ent r="3" t="760" w="856" /><ent r="3" t="760" w="866" /><ent r="3" t="760" w="876" /><ent r="3" t="760" w="886" /><ent r="3" t="760" w="902" /><ent r="3" t="760" w="1275" /><ent r="3" t="760" w="1285" /><ent r="3" t="760" w="1295" /><ent r="3" t="760" w="1305" /></phr></stem><stem n="-2012-02-12"><phr n="-2012-02-12"><ent r="3" t="760" w="429" /><ent r="3" t="760" w="431" /><ent r="3" t="760" w="661" /><ent r="3" t="760" w="663" /><ent r="3" t="760" w="858" /><ent r="3" t="760" w="860" /><ent r="3" t="760" w="1277" /><ent r="3" t="760" w="1279" /><ent r="3" t="760" w="1468" /><ent r="3" t="760" w="1470" /></phr></stem><stem n="cron-2012-02-12"><phr n="cron-2012-02-12"><ent r="3" t="760" w="429" /></phr></stem><stem n="2012-02-12"><phr n="2012-02-12"><ent r="3" t="760" w="430" /><ent r="3" t="760" w="662" /><ent r="3" t="760" w="859" /><ent r="3" t="760" w="1278" /><ent r="3" t="760" w="1469" /></phr></stem><stem n="02-12"><phr n="02-12"><ent r="3" t="760" w="431" /><ent r="3" t="760" w="663" /><ent r="3" t="760" w="860" /><ent r="3" t="760" w="1279" /><ent r="3" t="760" w="1470" /></phr></stem><stem n="-2012-02-19"><phr n="-2012-02-19"><ent r="3" t="760" w="439" /><ent r="3" t="760" w="441" /><ent r="3" t="760" w="671" /><ent r="3" t="760" w="673" /><ent r="3" t="760" w="868" /><ent r="3" t="760" w="870" /><ent r="3" t="760" w="1287" /><ent r="3" t="760" w="1289" /><ent r="3" t="760" w="1478" /><ent r="3" t="760" w="1480" /></phr></stem><stem n="cron-2012-02-19"><phr n="cron-2012-02-19"><ent r="3" t="760" w="439" /></phr></stem><stem n="2012-02-19"><phr n="2012-02-19"><ent r="3" t="760" w="440" /><ent r="3" t="760" w="672" /><ent r="3" t="760" w="869" /><ent r="3" t="760" w="1288" /><ent r="3" t="760" w="1479" /></phr></stem><stem n="02-19"><phr n="02-19"><ent r="3" t="760" w="441" /><ent r="3" t="760" w="673" /><ent r="3" t="760" w="870" /><ent r="3" t="760" w="1289" /><ent r="3" t="760" w="1480" /></phr></stem><stem n="cron-2012-02-22"><phr n="cron-2012-02-22"><ent r="3" t="760" w="449" /></phr></stem><stem n="dmesg"><phr n="dmesg"><ent r="3" t="760" w="459" /></phr></stem><stem n="18621"><phr n="18621"><ent r="3" t="760" w="460" /></phr></stem><stem n=":01"><phr n=":01"><ent r="3" t="760" w="464" /><ent r="3" t="760" w="1548" /></phr></stem><stem n="faillog"><phr n="faillog"><ent r="3" t="760" w="466" /></phr></stem><stem n="135830"><phr n="135830"><ent r="3" t="760" w="475" /></phr></stem><stem n="_dump_20110823074659"><phr n="_dump_20110823074659"><ent r="3" t="760" w="483" /></phr></stem><stem n="20110823074659"><phr n="20110823074659"><ent r="3" t="760" w="483" /></phr></stem><stem n="ksym"><phr n="ksyms"><ent r="3" t="760" w="489" /></phr></stem><stem n="lastlog"><phr n="lastlog"><ent r="3" t="760" w="495" /></phr></stem><stem n="21900"><phr n="21900"><ent r="3" t="760" w="496" /></phr></stem><stem n=":15"><phr n=":15"><ent r="3" t="760" w="500" /><ent r="3" t="760" w="1496" /></phr></stem><stem n="lost+found"><phr n="lost+found"><ent r="3" t="760" w="502" /></phr></stem><stem n="16384"><phr n="16384"><ent r="3" t="760" w="503" /></phr></stem><stem n=":49"><phr n=":49"><ent r="3" t="760" w="513" /></phr></stem><stem n="lunalogs-20101219"><phr n="lunalogs-20101219"><ent r="3" t="760" w="515" /></phr></stem><stem n="lunalogs-20101219-0402"><phr n="lunalogs-20101219-0402"><ent r="3" t="760" w="515" /></phr></stem><stem n="18707"><phr n="18707"><ent r="3" t="760" w="518" /></phr></stem><stem n="lunalogs-20101226"><phr n="lunalogs-20101226"><ent r="3" t="760" w="523" /></phr></stem><stem n="lunalogs-20101226-1432"><phr n="lunalogs-20101226-1432"><ent r="3" t="760" w="523" /></phr></stem><stem n="43097"><phr n="43097"><ent r="3" t="760" w="526" /></phr></stem><stem n="lunalogs-20110102"><phr n="lunalogs-20110102"><ent r="3" t="760" w="531" /></phr></stem><stem n="lunalogs-20110102-0402"><phr n="lunalogs-20110102-0402"><ent r="3" t="760" w="531" /></phr></stem><stem n="1393"><phr n="1393"><ent r="3" t="760" w="534" /></phr></stem><stem n="lunalogs-20110109"><phr n="lunalogs-20110109"><ent r="3" t="760" w="539" /></phr></stem><stem n="lunalogs-20110109-0402"><phr n="lunalogs-20110109-0402"><ent r="3" t="760" w="539" /></phr></stem><stem n="38650"><phr n="38650"><ent r="3" t="760" w="542" /></phr></stem><stem n="lunalogs-20110116"><phr n="lunalogs-20110116"><ent r="3" t="760" w="547" /></phr></stem><stem n="lunalogs-20110116-0402"><phr n="lunalogs-20110116-0402"><ent r="3" t="760" w="547" /></phr></stem><stem n="1754"><phr n="1754"><ent r="3" t="760" w="550" /></phr></stem><stem n="lunalogs-20110123"><phr n="lunalogs-20110123"><ent r="3" t="760" w="555" /></phr></stem><stem n="lunalogs-20110123-0402"><phr n="lunalogs-20110123-0402"><ent r="3" t="760" w="555" /></phr></stem><stem n="1441"><phr n="1441"><ent r="3" t="760" w="558" /></phr></stem><stem n="lunalogs-20110311"><phr n="lunalogs-20110311"><ent r="3" t="760" w="563" /></phr></stem><stem n="lunalogs-20110311-0402"><phr n="lunalogs-20110311-0402"><ent r="3" t="760" w="563" /></phr></stem><stem n="32696"><phr n="32696"><ent r="3" t="760" w="566" /></phr></stem><stem n="lunalogs-20110402"><phr n="lunalogs-20110402"><ent r="3" t="760" w="571" /></phr></stem><stem n="lunalogs-20110402-0402"><phr n="lunalogs-20110402-0402"><ent r="3" t="760" w="571" /></phr></stem><stem n="174984"><phr n="174984"><ent r="3" t="760" w="574" /></phr></stem><stem n="-20110405-0402"><phr n="-20110405-0402"><ent r="3" t="760" w="579" /><ent r="3" t="760" w="580" /><ent r="3" t="760" w="1386" /><ent r="3" t="760" w="1387" /></phr></stem><stem n="lunalogs-20110405"><phr n="lunalogs-20110405"><ent r="3" t="760" w="579" /></phr></stem><stem n="lunalogs-20110405-0402"><phr n="lunalogs-20110405-0402"><ent r="3" t="760" w="579" /></phr></stem><stem n="20110405"><phr n="20110405"><ent r="3" t="760" w="580" /><ent r="3" t="760" w="929" /><ent r="3" t="760" w="1387" /></phr></stem><stem n="20110405-0402"><phr n="20110405-0402"><ent r="3" t="760" w="580" /><ent r="3" t="760" w="929" /><ent r="3" t="760" w="1387" /></phr></stem><stem n="5274"><phr n="5274"><ent r="3" t="760" w="582" /></phr></stem><stem n="lunalogs-20110410"><phr n="lunalogs-20110410"><ent r="3" t="760" w="587" /></phr></stem><stem n="lunalogs-20110410-0402"><phr n="lunalogs-20110410-0402"><ent r="3" t="760" w="587" /></phr></stem><stem n="19109"><phr n="19109"><ent r="3" t="760" w="590" /></phr></stem><stem n="lunalogs-20110417"><phr n="lunalogs-20110417"><ent r="3" t="760" w="595" /></phr></stem><stem n="lunalogs-20110417-0402"><phr n="lunalogs-20110417-0402"><ent r="3" t="760" w="595" /></phr></stem><stem n="30395"><phr n="30395"><ent r="3" t="760" w="598" /></phr></stem><stem n="lunalogs-20110424"><phr n="lunalogs-20110424"><ent r="3" t="760" w="603" /></phr></stem><stem n="lunalogs-20110424-0402"><phr n="lunalogs-20110424-0402"><ent r="3" t="760" w="603" /></phr></stem><stem n="6867"><phr n="6867"><ent r="3" t="760" w="606" /></phr></stem><stem n="lunalogs-20110501"><phr n="lunalogs-20110501"><ent r="3" t="760" w="611" /></phr></stem><stem n="lunalogs-20110501-0402"><phr n="lunalogs-20110501-0402"><ent r="3" t="760" w="611" /></phr></stem><stem n="3246"><phr n="3246"><ent r="3" t="760" w="614" /></phr></stem><stem n="lunalogs-20110508"><phr n="lunalogs-20110508"><ent r="3" t="760" w="619" /></phr></stem><stem n="lunalogs-20110508-0102"><phr n="lunalogs-20110508-0102"><ent r="3" t="760" w="619" /></phr></stem><stem n="7581"><phr n="7581"><ent r="3" t="760" w="622" /></phr></stem><stem n="lunalogs-20110516"><phr n="lunalogs-20110516"><ent r="3" t="760" w="627" /></phr></stem><stem n="lunalogs-20110516-0833"><phr n="lunalogs-20110516-0833"><ent r="3" t="760" w="627" /></phr></stem><stem n="12366"><phr n="12366"><ent r="3" t="760" w="630" /></phr></stem><stem n="lunalogs-20110714"><phr n="lunalogs-20110714"><ent r="3" t="760" w="635" /></phr></stem><stem n="lunalogs-20110714-0402"><phr n="lunalogs-20110714-0402"><ent r="3" t="760" w="635" /></phr></stem><stem n="14078"><phr n="14078"><ent r="3" t="760" w="638" /></phr></stem><stem n="lunalogs-20110823"><phr n="lunalogs-20110823"><ent r="3" t="760" w="643" /></phr></stem></index>